async_graph_data_flow/__init__.py
async_graph_data_flow/executor.py
async_graph_data_flow/graph.py
async_graph_data_flow/py.typed
async_graph_data_flow-1.6.0.dist-info/LICENSE.txt
async_graph_data_flow-1.6.0.dist-info/METADATA
async_graph_data_flow-1.6.0.dist-info/WHEEL
async_graph_data_flow-1.6.0.dist-info/top_level.txt
async_graph_data_flow-1.6.0.dist-info/RECORD
