Metadata-Version: 2.2
Name: async-graph-data-flow
Version: 1.6.0
Summary: Asynchronous functions that pass data along a directed acyclic graph
Author-email: Civis Analytics <opensource@civisanalytics.com>
License: BSD 3-Clause
Project-URL: Documentation, https://async-graph-data-flow.readthedocs.io
Project-URL: Source, https://github.com/civisanalytics/async-graph-data-flow
Keywords: async,asynchronous,asyncio,data flow,graph
Classifier: Development Status :: 5 - Production/Stable
Classifier: Intended Audience :: Developers
Classifier: Intended Audience :: Information Technology
Classifier: Intended Audience :: Science/Research
Classifier: License :: OSI Approved :: BSD License
Classifier: Operating System :: OS Independent
Classifier: Programming Language :: Python :: 3
Classifier: Programming Language :: Python :: 3 :: Only
Classifier: Programming Language :: Python :: 3.10
Classifier: Programming Language :: Python :: 3.11
Classifier: Programming Language :: Python :: 3.12
Classifier: Programming Language :: Python :: 3.13
Classifier: Framework :: AsyncIO
Requires-Python: >=3.10
License-File: LICENSE.txt
Provides-Extra: dev
Requires-Dist: black==25.1.0; extra == "dev"
Requires-Dist: flake8==7.1.2; extra == "dev"
Requires-Dist: pytest==8.3.5; extra == "dev"
Requires-Dist: mypy==1.15.0; extra == "dev"
Requires-Dist: build==1.2.2; extra == "dev"
Requires-Dist: twine==6.1.0; extra == "dev"
Provides-Extra: docs
Requires-Dist: Sphinx==8.2.3; extra == "docs"
Requires-Dist: furo==2024.8.6; extra == "docs"
Requires-Dist: numpydoc==1.8.0; extra == "docs"
Requires-Dist: sphinx-copybutton==0.5.2; extra == "docs"
Requires-Dist: sphinxcontrib-mermaid==1.0.0; extra == "docs"
